Metadata-Version: 2.1
Name: CC-EXPTS
Version: 0.6
Summary: CC EXPTS + SC EXPTS package
Author: Ishannaik
Author-email: ishannaik7@gmail.com
